redshift_utils_mcp/__init__.py
redshift_utils_mcp/__main__.py
redshift_utils_mcp/formatting_utils.py
redshift_utils_mcp/server.py
redshift_utils_mcp/prompts/handlers.py
redshift_utils_mcp/resources/__init__.py
redshift_utils_mcp/resources/handlers.py
redshift_utils_mcp/sql_scripts/health/current_queries_status.sql
redshift_utils_mcp/sql_scripts/health/disk_usage.sql
redshift_utils_mcp/sql_scripts/health/dist_skew_count.sql
redshift_utils_mcp/sql_scripts/health/no_sort_key_count.sql
redshift_utils_mcp/sql_scripts/health/queued_vs_total_queries.sql
redshift_utils_mcp/sql_scripts/health/top_alerts.sql
redshift_utils_mcp/sql_scripts/health/underrepped_blocks.sql
redshift_utils_mcp/sql_scripts/locks/blocking_pids.sql
redshift_utils_mcp/sql_scripts/locks/running_transaction_locks.sql
redshift_utils_mcp/sql_scripts/query_perf/compilation_time.sql
redshift_utils_mcp/sql_scripts/query_perf/explain_plan.sql
redshift_utils_mcp/sql_scripts/query_perf/historical_runs.sql
redshift_utils_mcp/sql_scripts/query_perf/overall_metrics.sql
redshift_utils_mcp/sql_scripts/query_perf/query_alerts.sql
redshift_utils_mcp/sql_scripts/query_perf/query_text.sql
redshift_utils_mcp/sql_scripts/query_perf/segment_metrics.sql
redshift_utils_mcp/sql_scripts/query_perf/slice_skew.sql
redshift_utils_mcp/sql_scripts/resources/get_wlm_config.sql
redshift_utils_mcp/sql_scripts/resources/list_schemas.sql
redshift_utils_mcp/sql_scripts/resources/list_tables.sql
redshift_utils_mcp/sql_scripts/table_inspect/get_oid.sql
redshift_utils_mcp/sql_scripts/table_inspect/get_table_ddl.sql
redshift_utils_mcp/sql_scripts/table_inspect/missing_stats_count.sql
redshift_utils_mcp/sql_scripts/table_inspect/needs_vacuum_count.sql
redshift_utils_mcp/sql_scripts/table_inspect/scan_frequency.sql
redshift_utils_mcp/sql_scripts/table_inspect/stale_stats_count.sql
redshift_utils_mcp/sql_scripts/table_inspect/table_info.sql
redshift_utils_mcp/sql_scripts/table_inspect/table_inspector.sql
redshift_utils_mcp-0.3.4.dist-info/METADATA
redshift_utils_mcp-0.3.4.dist-info/WHEEL
redshift_utils_mcp-0.3.4.dist-info/entry_points.txt
redshift_utils_mcp-0.3.4.dist-info/licenses/LICENSE
redshift_utils_mcp-0.3.4.dist-info/RECORD
