Metadata-Version: 2.4
Name: redshift-utils-mcp
Version: 0.3.4
Summary: A Python-based MCP server for database actions on Amazon Redshift using the Data API
Project-URL: Homepage, https://github.com/vinodismyname/redshift-utils-mcp
Project-URL: Documentation, https://github.com/vinodismyname/redshift-utils-mcp#readme
Project-URL: Repository, https://github.com/vinodismyname/redshift-utils-mcp
Project-URL: Issues, https://github.com/vinodismyname/redshift-utils-mcp/issues
Author-email: Vinod <vinodismyname@users.noreply.github.com>
License: MIT
License-File: LICENSE
Keywords: aws,database,mcp,model-context-protocol,redshift
Classifier: License :: OSI Approved :: MIT License
Classifier: Operating System :: OS Independent
Classifier: Programming Language :: Python :: 3
Requires-Python: >=3.10
Requires-Dist: boto3>=1.34.0
Requires-Dist: fastmcp>=2.2.5
Requires-Dist: pydantic>=2.0
Requires-Dist: pytest-asyncio>=0.26.0
Requires-Dist: pytest>=8.3.5
Requires-Dist: python-dotenv>=1.0.0
Requires-Dist: typer>=0.15.2
Requires-Dist: typing-extensions>=4.13.2
Provides-Extra: dev
Requires-Dist: pytest-asyncio>=0.23.0; extra == 'dev'
Requires-Dist: pytest>=8.0.0; extra == 'dev'
